{
  "db": "PostgreSQL",
  "9bccc69722158ef1ba713128114cef2ea125f804da57460cfbea283217dd128c": {
    "query": "\n        DELETE FROM subscriptions\n        WHERE email = 'ursula_le_guin@gmail.com';\n        ",
    "describe": {
      "columns": [],
      "parameters": {
        "Left": []
      },
      "nullable": []
    }
  },
  "b1e51d9c64b3d93ee881899d26635b16e52c349294d7d190d01ee665f2ec5a72": {
    "query": "\n        INSERT INTO subscriptions(id, email, name, subscribed_at)\n        VALUES ($1, $2, $3, $4);\n        ",
    "describe": {
      "columns": [],
      "parameters": {
        "Left": [
          "Uuid",
          "Text",
          "Text",
          "Timestamptz"
        ]
      },
      "nullable": []
    }
  }
}